evasif/__about__.py
evasif/__init__.py
evasif-0.0.1.dist-info/METADATA
evasif-0.0.1.dist-info/WHEEL
evasif-0.0.1.dist-info/licenses/LICENCE
evasif-0.0.1.dist-info/RECORD
