Metadata-Version: 2.4
Name: evasif
Version: 0.0.1
Project-URL: Documentation, https://github.com/turbotice/evasif#readme
Project-URL: Issues, https://github.com/turbotice/evasif/issues
Project-URL: Source, https://github.com/turbotice/evasif
Author-email: Nicolas Mokus <nmks@tuta.io>
License-Expression: MIT
License-File: LICENCE
Classifier: Development Status :: 3 - Alpha
Classifier: Intended Audience :: Science/Research
Classifier: License :: OSI Approved :: MIT License
Classifier: Natural Language :: English
Classifier: Operating System :: OS Independent
Classifier: Programming Language :: Python
Classifier: Programming Language :: Python :: 3.12
Classifier: Programming Language :: Python :: 3.13
Classifier: Programming Language :: Python :: Implementation :: CPython
Classifier: Topic :: Scientific/Engineering :: Oceanography
Classifier: Topic :: Scientific/Engineering :: Physics
Requires-Python: >=3.12
Requires-Dist: attrs
Requires-Dist: cmocean
Requires-Dist: matplotlib
Requires-Dist: numpy
Requires-Dist: scipy
